Metadata-Version: 2.1
Name: metawarc
Version: 1.1.1
Summary: metawarc: a command-line tool for data extraction from WARC files (web archives)
Home-page: https://github.com/datacoon/metawarc/
Download-URL: https://github.com/datacoon/metawarc/
Author: Ivan Begtin
Author-email: ivan@begtin.tech
License: MIT
Keywords: warc archive webarchive metadata
Platform: UNKNOWN
Classifier: Development Status :: 5 - Production/Stable
Classifier: Programming Language :: Python
Classifier: Programming Language :: Python :: 3 :: Only
Classifier: Programming Language :: Python :: 3.6
Classifier: Programming Language :: Python :: 3.7
Classifier: Environment :: Console
Classifier: Intended Audience :: Developers
Classifier: Intended Audience :: System Administrators
Classifier: License :: OSI Approved :: BSD License
Classifier: Topic :: Software Development
Classifier: Topic :: System :: Networking
Classifier: Topic :: Terminals
Classifier: Topic :: Text Processing
Classifier: Topic :: Utilities
Provides-Extra: python_version == "3.0" or python_version == "3.1"
License-File: LICENSE
License-File: AUTHORS.rst
